unload_packages/__init__.py
unload_packages-0.1.0.dist-info/LICENSE
unload_packages-0.1.0.dist-info/METADATA
unload_packages-0.1.0.dist-info/WHEEL
unload_packages-0.1.0.dist-info/top_level.txt
unload_packages-0.1.0.dist-info/RECORD
