Metadata-Version: 2.1
Name: unload_packages
Version: 0.1.0
Summary: Simple package reloader for Maya, Unreal, or other DCCs.
Author-email: Gabe Reed <gabrieljreed@gmail.com>
License: MIT License
Project-URL: Homepage, https://github.com/gabrieljreed/PythonPackageReloader
Project-URL: Bug Tracker, https://github.com/gabrieljreed/PythonPackageReloader/issues
Requires-Python: >=2.7.0
License-File: LICENSE
